obsession/__init__.py
obsession-1.2.1.dist-info/LICENSE.txt
obsession-1.2.1.dist-info/METADATA
obsession-1.2.1.dist-info/WHEEL
obsession-1.2.1.dist-info/top_level.txt
obsession-1.2.1.dist-info/RECORD
