Metadata-Version: 2.1
Name: obsession
Version: 1.2.1
Summary: Server-side HTTP sessions
Home-page: https://hg.sr.ht/~olly/obsession/
Author: Oliver Cope
Author-email: oliver@redgecko.org
License: Apache
Keywords: wsgi session sessions management cookie
Classifier: Development Status :: 5 - Production/Stable
Classifier: Environment :: Web Environment
Classifier: Intended Audience :: Developers
Classifier: License :: OSI Approved :: Apache Software License
Classifier: Operating System :: OS Independent
Classifier: Programming Language :: Python
Classifier: Programming Language :: Python :: 3
Classifier: Programming Language :: Python :: 3 :: Only
Classifier: Topic :: Internet :: WWW/HTTP :: Dynamic Content
Classifier: Topic :: Internet :: WWW/HTTP :: WSGI
Classifier: Topic :: Software Development :: Libraries :: Python Modules
License-File: LICENSE.txt
